
{
  // from Element: extension
  "origin" : { Quantity(SimpleQuantity) }, // R!  Zero value and units
  "period" : <decimal>, // R!  Number of milliseconds between samples
  "factor" : <decimal>, // Multiply data by this before adding to origin
  "lowerLimit" : <decimal>, // Lower limit of detection
  "upperLimit" : <decimal>, // Upper limit of detection
  "dimensions" : "<positiveInt>", // R!  Number of sample points at each time point
  "data" : "<string>" // R!  Decimal values with spaces, or "E" | "U" | "L"
}
